gisl_data_library/__init__.py
gisl_data_library/gisl.py
gisl_data_library/gisl_data.json
gisl_data_library-0.1.5.dist-info/METADATA
gisl_data_library-0.1.5.dist-info/WHEEL
gisl_data_library-0.1.5.dist-info/top_level.txt
gisl_data_library-0.1.5.dist-info/RECORD
