Metadata-Version: 2.4
Name: gisl-data-library
Version: 0.1.5
Summary: A static library of Genshin item/char info. (WIP) - Albedo added.
Home-page: https://github.com/Imran-Delta/GI-Static-Data-Library
Author: Imran Bin Gifary (System Delta or Imran Delta Online)
Author-email: imran.sdelta@gmail.com
Dynamic: author
Dynamic: author-email
Dynamic: description
Dynamic: description-content-type
Dynamic: home-page
Dynamic: summary
